setup.py
slackapi.py
python_slackapi.egg-info/PKG-INFO
python_slackapi.egg-info/SOURCES.txt
python_slackapi.egg-info/dependency_links.txt
python_slackapi.egg-info/top_level.txt
test/test.py