Metadata-Version: 1.0
Name: python-slackapi
Version: 0.1.1
Summary: Python Simple Slack Event Api
Home-page: https://github.com/JSpiner/SlackApi
Author: JSpiner
Author-email: jspiner@naver.com
License: UNKNOWN
Platform: UNKNOWN
